{"doc_id": "f9f2c09d-e9ed-4bdb-9a70-93993771b2e0", "doc_name": "Dog Sickness Detection", "doc_version": "d7bef3402d73e8ad53aef13fe9187f5d", "format": "tf_js", "version": 16, "inputs": {"Image": {"dtype": "float32", "shape": [null, 224, 224, 3], "name": "Image:0"}}, "outputs": {"Confidences": {"dtype": "float32", "shape": [null, 2], "name": "f9f2c09d-e9ed-4bdb-9a70-93993771b2e0.ee257072-bafd-42b5-a7d5-74be6c513409/dense_2/Softmax:0"}}, "tags": null, "classes": {"Label": ["Dogs", "Sick Dogs"]}, "filename": "model.json", "export_model_version": 1}